[
    {
        "contract_code": "BTC220708",
        "contract_size": 100.0,
        "contract_status": 1,
        "contract_type": "this_week",
        "create_date": "20220624",
        "delivery_date": "20220708",
        "delivery_time": "1657267200000",
        "price_tick": 0.01,
        "settlement_time": "1657094400000",
        "symbol": "BTC"
    },
    {
        "contract_code": "BTC220715",
        "contract_size": 100.0,
        "contract_status": 1,
        "contract_type": "next_week",
        "create_date": "20220701",
        "delivery_date": "20220715",
        "delivery_time": "1657872000000",
        "price_tick": 0.01,
        "settlement_time": "1657094400000",
        "symbol": "BTC"
    },
    {
        "contract_code": "BTC220930",
        "contract_size": 100.0,
        "contract_status": 1,
        "contract_type": "quarter",
        "create_date": "20220311",
        "delivery_date": "20220930",
        "delivery_time": "1664524800000",
        "price_tick": 0.01,
        "settlement_time": "1657094400000",
        "symbol": "BTC"
    },
    {
        "contract_code": "ETH220708",
        "contract_size": 10.0,
        "contract_status": 1,
        "contract_type": "this_week",
        "create_date": "20220624",
        "delivery_date": "20220708",
        "delivery_time": "1657267200000",
        "price_tick": 0.001,
        "settlement_time": "1657094400000",
        "symbol": "ETH"
    },
    {
        "contract_code": "ETH220715",
        "contract_size": 10.0,
        "contract_status": 1,
        "contract_type": "next_week",
        "create_date": "20220701",
        "delivery_date": "20220715",
        "delivery_time": "1657872000000",
        "price_tick": 0.001,
        "settlement_time": "1657094400000",
        "symbol": "ETH"
    },
    {
        "contract_code": "ETH220930",
        "contract_size": 10.0,
        "contract_status": 1,
        "contract_type": "quarter",
        "create_date": "20220311",
        "delivery_date": "20220930",
        "delivery_time": "1664524800000",
        "price_tick": 0.001,
        "settlement_time": "1657094400000",
        "symbol": "ETH"
    },
    {
        "contract_code": "LTC220708",
        "contract_size": 10.0,
        "contract_status": 1,
        "contract_type": "this_week",
        "create_date": "20220624",
        "delivery_date": "20220708",
        "delivery_time": "1657267200000",
        "price_tick": 0.001,
        "settlement_time": "1657094400000",
        "symbol": "LTC"
    },
    {
        "contract_code": "LTC220715",
        "contract_size": 10.0,
        "contract_status": 1,
        "contract_type": "next_week",
        "create_date": "20220701",
        "delivery_date": "20220715",
        "delivery_time": "1657872000000",
        "price_tick": 0.001,
        "settlement_time": "1657094400000",
        "symbol": "LTC"
    },
    {
        "contract_code": "LTC220930",
        "contract_size": 10.0,
        "contract_status": 1,
        "contract_type": "quarter",
        "create_date": "20220311",
        "delivery_date": "20220930",
        "delivery_time": "1664524800000",
        "price_tick": 0.001,
        "settlement_time": "1657094400000",
        "symbol": "LTC"
    },
    {
        "contract_code": "EOS220708",
        "contract_size": 10.0,
        "contract_status": 1,
        "contract_type": "this_week",
        "create_date": "20220624",
        "delivery_date": "20220708",
        "delivery_time": "1657267200000",
        "price_tick": 0.001,
        "settlement_time": "1657094400000",
        "symbol": "EOS"
    },
    {
        "contract_code": "EOS220715",
        "contract_size": 10.0,
        "contract_status": 1,
        "contract_type": "next_week",
        "create_date": "20220701",
        "delivery_date": "20220715",
        "delivery_time": "1657872000000",
        "price_tick": 0.001,
        "settlement_time": "1657094400000",
        "symbol": "EOS"
    },
    {
        "contract_code": "LINK220708",
        "contract_size": 10.0,
        "contract_status": 1,
        "contract_type": "this_week",
        "create_date": "20220624",
        "delivery_date": "20220708",
        "delivery_time": "1657267200000",
        "price_tick": 0.0001,
        "settlement_time": "1657094400000",
        "symbol": "LINK"
    },
    {
        "contract_code": "LINK220715",
        "contract_size": 10.0,
        "contract_status": 1,
        "contract_type": "next_week",
        "create_date": "20220701",
        "delivery_date": "20220715",
        "delivery_time": "1657872000000",
        "price_tick": 0.0001,
        "settlement_time": "1657094400000",
        "symbol": "LINK"
    },
    {
        "contract_code": "DOT220708",
        "contract_size": 10.0,
        "contract_status": 1,
        "contract_type": "this_week",
        "create_date": "20220624",
        "delivery_date": "20220708",
        "delivery_time": "1657267200000",
        "price_tick": 0.0001,
        "settlement_time": "1657094400000",
        "symbol": "DOT"
    },
    {
        "contract_code": "DOT220715",
        "contract_size": 10.0,
        "contract_status": 1,
        "contract_type": "next_week",
        "create_date": "20220701",
        "delivery_date": "20220715",
        "delivery_time": "1657872000000",
        "price_tick": 0.0001,
        "settlement_time": "1657094400000",
        "symbol": "DOT"
    },
    {
        "contract_code": "TRX220708",
        "contract_size": 10.0,
        "contract_status": 1,
        "contract_type": "this_week",
        "create_date": "20220624",
        "delivery_date": "20220708",
        "delivery_time": "1657267200000",
        "price_tick": 1e-05,
        "settlement_time": "1657094400000",
        "symbol": "TRX"
    },
    {
        "contract_code": "TRX220715",
        "contract_size": 10.0,
        "contract_status": 1,
        "contract_type": "next_week",
        "create_date": "20220701",
        "delivery_date": "20220715",
        "delivery_time": "1657872000000",
        "price_tick": 1e-05,
        "settlement_time": "1657094400000",
        "symbol": "TRX"
    },
    {
        "contract_code": "ADA220708",
        "contract_size": 10.0,
        "contract_status": 1,
        "contract_type": "this_week",
        "create_date": "20220624",
        "delivery_date": "20220708",
        "delivery_time": "1657267200000",
        "price_tick": 1e-06,
        "settlement_time": "1657094400000",
        "symbol": "ADA"
    },
    {
        "contract_code": "ADA220715",
        "contract_size": 10.0,
        "contract_status": 1,
        "contract_type": "next_week",
        "create_date": "20220701",
        "delivery_date": "20220715",
        "delivery_time": "1657872000000",
        "price_tick": 1e-06,
        "settlement_time": "1657094400000",
        "symbol": "ADA"
    },
    {
        "contract_code": "BCH220708",
        "contract_size": 10.0,
        "contract_status": 1,
        "contract_type": "this_week",
        "create_date": "20220624",
        "delivery_date": "20220708",
        "delivery_time": "1657267200000",
        "price_tick": 0.001,
        "settlement_time": "1657094400000",
        "symbol": "BCH"
    },
    {
        "contract_code": "BCH220715",
        "contract_size": 10.0,
        "contract_status": 1,
        "contract_type": "next_week",
        "create_date": "20220701",
        "delivery_date": "20220715",
        "delivery_time": "1657872000000",
        "price_tick": 0.001,
        "settlement_time": "1657094400000",
        "symbol": "BCH"
    },
    {
        "contract_code": "XRP220708",
        "contract_size": 10.0,
        "contract_status": 1,
        "contract_type": "this_week",
        "create_date": "20220624",
        "delivery_date": "20220708",
        "delivery_time": "1657267200000",
        "price_tick": 0.0001,
        "settlement_time": "1657094400000",
        "symbol": "XRP"
    },
    {
        "contract_code": "XRP220715",
        "contract_size": 10.0,
        "contract_status": 1,
        "contract_type": "next_week",
        "create_date": "20220701",
        "delivery_date": "20220715",
        "delivery_time": "1657872000000",
        "price_tick": 0.0001,
        "settlement_time": "1657094400000",
        "symbol": "XRP"
    },
    {
        "contract_code": "BSV220708",
        "contract_size": 10.0,
        "contract_status": 1,
        "contract_type": "this_week",
        "create_date": "20220624",
        "delivery_date": "20220708",
        "delivery_time": "1657267200000",
        "price_tick": 0.001,
        "settlement_time": "1657094400000",
        "symbol": "BSV"
    },
    {
        "contract_code": "BSV220715",
        "contract_size": 10.0,
        "contract_status": 1,
        "contract_type": "next_week",
        "create_date": "20220701",
        "delivery_date": "20220715",
        "delivery_time": "1657872000000",
        "price_tick": 0.001,
        "settlement_time": "1657094400000",
        "symbol": "BSV"
    },
    {
        "contract_code": "ETC220708",
        "contract_size": 10.0,
        "contract_status": 1,
        "contract_type": "this_week",
        "create_date": "20220624",
        "delivery_date": "20220708",
        "delivery_time": "1657267200000",
        "price_tick": 0.001,
        "settlement_time": "1657094400000",
        "symbol": "ETC"
    },
    {
        "contract_code": "ETC220715",
        "contract_size": 10.0,
        "contract_status": 1,
        "contract_type": "next_week",
        "create_date": "20220701",
        "delivery_date": "20220715",
        "delivery_time": "1657872000000",
        "price_tick": 0.001,
        "settlement_time": "1657094400000",
        "symbol": "ETC"
    },
    {
        "contract_code": "FIL220708",
        "contract_size": 10.0,
        "contract_status": 1,
        "contract_type": "this_week",
        "create_date": "20220624",
        "delivery_date": "20220708",
        "delivery_time": "1657267200000",
        "price_tick": 0.001,
        "settlement_time": "1657094400000",
        "symbol": "FIL"
    },
    {
        "contract_code": "FIL220715",
        "contract_size": 10.0,
        "contract_status": 1,
        "contract_type": "next_week",
        "create_date": "20220701",
        "delivery_date": "20220715",
        "delivery_time": "1657872000000",
        "price_tick": 0.001,
        "settlement_time": "1657094400000",
        "symbol": "FIL"
    }
]
